msflta/__init__.py
msflta/mc_nfcfs.py
msflta/mc_wfcfs.py
msflta/mechanism_fc_nfcfs.py
msflta/mechanism_fc_wfcfs.py
msflta/mechanism_gs_nfcfs.py
msflta/mechanism_gs_wfcfs.py
msflta/sc_nfcfs.py
msflta/sc_nfcfs_mov.py
msflta/sc_wfcfs.py
msflta/sc_wfcfs_mov.py
msflta/util.py
msflta-1.0.3.dist-info/LICENSE
msflta-1.0.3.dist-info/METADATA
msflta-1.0.3.dist-info/WHEEL
msflta-1.0.3.dist-info/top_level.txt
msflta-1.0.3.dist-info/RECORD
