Metadata-Version: 2.1
Name: msflta
Version: 1.0.3
Summary: This is the python package implementing several algorithms and strategy-proof mechanisms introduced in the paper Multi-stage Facility Location Problem with Transient Agents
Author-email: Xuezhen Wang <xuezhenwang2@gmail.com>
License: The MIT License (MIT)
Project-URL: Homepage, https://github.com/William-WANG2/FYP-CityU
Keywords: algorithms,strategy-proof mechanisms,facility location problem
Classifier: License :: OSI Approved :: MIT License
Classifier: Programming Language :: Python
Classifier: Programming Language :: Python :: 3
Requires-Python: >=3.7
License-File: LICENSE
Requires-Dist: numpy (>=1.21.5)
Provides-Extra: dev
Requires-Dist: black ; extra == 'dev'
Requires-Dist: bumpver ; extra == 'dev'
Requires-Dist: isort ; extra == 'dev'
Requires-Dist: pip-tools ; extra == 'dev'
Requires-Dist: pytest ; extra == 'dev'
